CHANGES.rst
LICENSE
MANIFEST.in
README.rst
setup.py
Flask_JinjaHelpers.egg-info/PKG-INFO
Flask_JinjaHelpers.egg-info/SOURCES.txt
Flask_JinjaHelpers.egg-info/dependency_links.txt
Flask_JinjaHelpers.egg-info/not-zip-safe
Flask_JinjaHelpers.egg-info/requires.txt
Flask_JinjaHelpers.egg-info/top_level.txt
flask_jinjahelpers/__init__.py
flask_jinjahelpers/templates/_formhelpers.html
flask_jinjahelpers/templates/_generic_modals.html
flask_jinjahelpers/templates/_messages.html
flask_jinjahelpers/templates/_tablehelpers.html
tests/__init__.py
tests/test_header_sorter.py
tests/test_visible_page_numbers.py